simple_kfp_task/__init__.py
simple_kfp_task/task.py
simple_kfp_task_stub-0.0.4.dist-info/LICENSE
simple_kfp_task_stub-0.0.4.dist-info/METADATA
simple_kfp_task_stub-0.0.4.dist-info/WHEEL
simple_kfp_task_stub-0.0.4.dist-info/top_level.txt
simple_kfp_task_stub-0.0.4.dist-info/RECORD
