Metadata-Version: 2.1
Name: simple-kfp-task-stub
Version: 0.0.4
Summary: Generate a simple Kubeflow Pipeline task
Author-email: Sebastian Alberternst <sebastian.alberternst@dfki.de>
Project-URL: Homepage, https://github.com/salberternst/simple-kfp-task-stub
Project-URL: Issues, https://github.com/salberternst/simple-kfp-task-stub/issues
Classifier: Programming Language :: Python :: 3
Classifier: License :: OSI Approved :: MIT License
Classifier: Operating System :: OS Independent
Requires-Python: >=3.8
License-File: LICENSE
